testbot/__init__.py
testbot/cli.py
testbot/app/TestApplicationBase.py
testbot/app/TestCaseBase.py
testbot/app/TestToolBase.py
testbot/app/__init__.py
testbot/app/decorator.py
testbot/app/designer.html
testbot/app/precondition.py
testbot/config/ResourceSetting.json
testbot/config/TestClass_MySetting.json
testbot/config/__init__.py
testbot/config/logicmodule.py
testbot/config/setting.py
testbot/config/static_setting.py
testbot/config/static_setting_demo.py
testbot/contrib/__init__.py
testbot/contrib/base/__init__.py
testbot/contrib/base/settings.py
testbot/contrib/base/apps/__init__.py
testbot/contrib/base/apps/scripts/__init__.py
testbot/contrib/base/apps/scripts/templates/CNTC-94402_恢复出厂设置.py
testbot/contrib/base/apps/scripts/templates/TCList.json
testbot/contrib/base/apps/scripts/templates/TCListSetting.json
testbot/contrib/base/apps/scripts/templates/__init__.py
testbot/contrib/base/apps/scripts/unit_test/TCList.json
testbot/contrib/base/apps/scripts/unit_test/TCListSetting.json
testbot/contrib/base/apps/scripts/unit_test/TcDemo.py
testbot/contrib/base/apps/scripts/unit_test/TcDemoSetting.json
testbot/contrib/base/apps/scripts/unit_test/__init__.py
testbot/contrib/base/apps/scripts/unit_test/pool.html
testbot/contrib/base/apps/scripts/unit_test/pool.json
testbot/contrib/base/apps/scripts/unit_test/result.html
testbot/contrib/base/apps/scripts/unit_test/result.json
testbot/contrib/base/apps/tools/__init__.py
testbot/contrib/base/apps/tools/templates/__init__.py
testbot/contrib/base/apps/tools/templates/媒体资讯遍历工具.py
testbot/contrib/base/plugins/DemoPlugin.py
testbot/contrib/base/plugins/LogkitPlugin.py
testbot/contrib/base/plugins/__init__.py
testbot/contrib/base/resources/ResourcePool.py
testbot/contrib/base/resources/__init__.py
testbot/contrib/base/resources/devices/__init__.py
testbot/contrib/base/resources/devices/AndroidDevice/AndroidDevice.py
testbot/contrib/base/resources/devices/AndroidDevice/AndroidDeviceAtomModuleBase.py
pytestbot-2025.12.422.dist-info/LICENSE
pytestbot-2025.12.422.dist-info/METADATA
pytestbot-2025.12.422.dist-info/WHEEL
pytestbot-2025.12.422.dist-info/entry_points.txt
pytestbot-2025.12.422.dist-info/top_level.txt
pytestbot-2025.12.422.dist-info/RECORD
