Metadata-Version: 2.2
Name: pytestbot
Version: 2025.12.422
Summary: 一款支持手机、电视、手表等智能硬件产品的自动化测试框架，提供开发测试工具、开发测试脚本、扩展基础原子接口、扩展业务封装接口、扩展测试插件等使用支持。最新版本基于分支: master和提交ID: 6a372d3所编译生成
Home-page: https://pypi.org/project/pytestbot/
Author: Nuanguang Gu(Sunny)
Author-email: nuanguang.gu@aliyun.com
License: Copyright (c) 2024 Nuanguang Gu(Sunny) Reserved
Project-URL: Bug Reports, https://gitee.com/nuangua/testbot/issues
Project-URL: Source, https://gitee.com/nuangua/testbot
Keywords: testbot,pytestbot
Classifier: Development Status :: 3 - Alpha
Classifier: Intended Audience :: Developers
Classifier: Topic :: Software Development :: Build Tools
Classifier: Programming Language :: Python :: 3.7
Classifier: Programming Language :: Python :: 3.8
Classifier: Programming Language :: Python :: 3.9
Classifier: Programming Language :: Python :: 3 :: Only
Requires-Python: >=3.8, <4
License-File: LICENSE
Requires-Dist: adbutils==2.5.0; python_version >= "3.8" and sys_platform == "win32" or python_version >= "3.8" and sys_platform == "linux" or python_version >= "3.8" and sys_platform == "darwin"
Requires-Dist: pkginfo==1.11.2; python_version >= "3.8" and sys_platform == "win32" or python_version >= "3.8" and sys_platform == "linux" or python_version >= "3.8" and sys_platform == "darwin"
Requires-Dist: click==8.1.7; python_version >= "3.8" and sys_platform == "win32" or python_version >= "3.8" and sys_platform == "linux" or python_version >= "3.8" and sys_platform == "darwin"
Requires-Dist: atlassian-python-api==3.41.16; python_version >= "3.8" and sys_platform == "win32" or python_version >= "3.8" and sys_platform == "linux" or python_version >= "3.8" and sys_platform == "darwin"
Requires-Dist: grpcio==1.68.0; python_version >= "3.8" and sys_platform == "win32" or python_version >= "3.8" and sys_platform == "linux" or python_version >= "3.8" and sys_platform == "darwin"
Requires-Dist: grpcio-tools==1.68.0; python_version >= "3.8" and sys_platform == "win32" or python_version >= "3.8" and sys_platform == "linux" or python_version >= "3.8" and sys_platform == "darwin"
Requires-Dist: protobuf==5.29.0; python_version >= "3.8" and sys_platform == "win32" or python_version >= "3.8" and sys_platform == "linux" or python_version >= "3.8" and sys_platform == "darwin"
Requires-Dist: imagehash==4.3.1; python_version >= "3.8" and sys_platform == "win32" or python_version >= "3.8" and sys_platform == "linux" or python_version >= "3.8" and sys_platform == "darwin"
Requires-Dist: pillow==10.3.0; python_version >= "3.8" and sys_platform == "win32" or python_version >= "3.8" and sys_platform == "linux" or python_version >= "3.8" and sys_platform == "darwin"
Requires-Dist: pyserial==3.5; python_version >= "3.8" and sys_platform == "win32" or python_version >= "3.8" and sys_platform == "linux" or python_version >= "3.8" and sys_platform == "darwin"
Requires-Dist: rst2html5==2.0; python_version >= "3.8" and sys_platform == "win32" or python_version >= "3.8" and sys_platform == "linux" or python_version >= "3.8" and sys_platform == "darwin"
Requires-Dist: docutils==0.19; python_version >= "3.8" and sys_platform == "win32" or python_version >= "3.8" and sys_platform == "linux" or python_version >= "3.8" and sys_platform == "darwin"
Requires-Dist: atlassian-python-api==3.41.16; python_version >= "3.8" and sys_platform == "win32" or python_version >= "3.8" and sys_platform == "linux" or python_version >= "3.8" and sys_platform == "darwin"
Requires-Dist: docstring_parser==0.16; python_version >= "3.8" and sys_platform == "win32" or python_version >= "3.8" and sys_platform == "linux" or python_version >= "3.8" and sys_platform == "darwin"
Requires-Dist: json2html==1.3.0; python_version >= "3.8" and sys_platform == "win32" or python_version >= "3.8" and sys_platform == "linux" or python_version >= "3.8" and sys_platform == "darwin"
Requires-Dist: pytest==7.2.0; python_version >= "3.8" and sys_platform == "win32" or python_version >= "3.8" and sys_platform == "linux" or python_version >= "3.8" and sys_platform == "darwin"
Requires-Dist: opencv-contrib-python==4.10.0.84; python_version >= "3.8" and sys_platform == "win32" or python_version >= "3.8" and sys_platform == "linux" or python_version >= "3.8" and sys_platform == "darwin"
Requires-Dist: opencv-python==4.10.0.84; python_version >= "3.8" and sys_platform == "win32" or python_version >= "3.8" and sys_platform == "linux" or python_version >= "3.8" and sys_platform == "darwin"
Requires-Dist: uiautomator2==3.2.5; python_version >= "3.8" and sys_platform == "win32" or python_version >= "3.8" and sys_platform == "linux" or python_version >= "3.8" and sys_platform == "darwin"
Dynamic: author
Dynamic: author-email
Dynamic: classifier
Dynamic: description
Dynamic: description-content-type
Dynamic: home-page
Dynamic: keywords
Dynamic: license
Dynamic: project-url
Dynamic: requires-dist
Dynamic: requires-python
Dynamic: summary
